tiinfer/__init__.py
tiinfer/__main__.py
tiinfer/_version.py
tiinfer/const.py
tiinfer/model.py
tiinfer/server.py
tiinfer/worker.py
tiinfer/utils/__init__.py
tiinfer/utils/imageutil.py
tiinfer/utils/ioutil.py
tencent_tiinfer-0.1.5.dist-info/METADATA
tencent_tiinfer-0.1.5.dist-info/WHEEL
tencent_tiinfer-0.1.5.dist-info/top_level.txt
tencent_tiinfer-0.1.5.dist-info/RECORD
